chipseqpeaks/ENCFF001TDO.bed.gz
chipseqpeaks/ENCFF419RSJ.bed.gz
chipseqpeaks/ENCFF547MET.bed.gz
chipseqpeaks/__init__.py
chipseqpeaks/call_peaks.py
chipseqpeaks/chip_seq_peaks.py
chipseqpeaks/doc.py
chipseqpeaks-1.1.5.dist-info/LICENSE
chipseqpeaks-1.1.5.dist-info/METADATA
chipseqpeaks-1.1.5.dist-info/WHEEL
chipseqpeaks-1.1.5.dist-info/entry_points.txt
chipseqpeaks-1.1.5.dist-info/top_level.txt
chipseqpeaks-1.1.5.dist-info/RECORD
