Metadata-Version: 2.1
Name: chipseqpeaks
Version: 1.1.5
Summary: Easy management of ChIP-seq peak calling
Home-page: https://gitlab.com/aaylward/chipseqpeaks
Author: Anthony Aylward, Joshua Chiou
Author-email: aaylward@esalk.edu
License: UNKNOWN
Platform: UNKNOWN
Classifier: Programming Language :: Python :: 3
Classifier: License :: OSI Approved :: MIT License
Classifier: Operating System :: OS Independent
License-File: LICENSE
